{
  "species": [
    "Dactylagnus mundus",
    "Dactylagnus parvus",
    "Dactylagnus peratikos",
    "Dactyloscopus amnis",
    "Dactyloscopus boehlkei",
    "Dactyloscopus byersi",
    "Dactyloscopus comptus",
    "Dactyloscopus crossotus",
    "Dactyloscopus elongatus",
    "Dactyloscopus fallax",
    "Dactyloscopus fimbriatus",
    "Dactyloscopus foraminosus",
    "Dactyloscopus heraldi",
    "Dactyloscopus insulatus",
    "Dactyloscopus lacteus",
    "Dactyloscopus lunaticus",
    "Dactyloscopus metoecus",
    "Dactyloscopus minutus",
    "Dactyloscopus moorei",
    "Dactyloscopus pectoralis",
    "Dactyloscopus poeyi",
    "Dactyloscopus tridigitatus",
    "Dactyloscopus zelotes",
    "Gillellus arenicola",
    "Gillellus chathamensis",
    "Gillellus greyae",
    "Gillellus healae",
    "Gillellus inescatus",
    "Gillellus jacksoni",
    "Gillellus ornatus",
    "Gillellus searcheri",
    "Gillellus semicinctus",
    "Gillellus uranidea",
    "Heteristius cinctus",
    "Leurochilus acon",
    "Myxodagnus belone",
    "Myxodagnus macrognathus",
    "Myxodagnus opercularis",
    "Myxodagnus sagitta",
    "Myxodagnus walkeri",
    "Platygillellus altivelis",
    "Platygillellus brasiliensis",
    "Platygillellus bussingi",
    "Platygillellus rubellulus",
    "Platygillellus rubrocinctus",
    "Platygillellus smithi",
    "Sindoscopus australis",
    "Storrsia olsoni"
  ],
  "sampled_species": [
    "Dactyloscopus lacteus",
    "Dactyloscopus pectoralis",
    "Gillellus semicinctus",
    "Gillellus uranidea",
    "Platygillellus rubrocinctus"
  ],
  "unsampled_species": [
    "Dactylagnus mundus",
    "Dactylagnus parvus",
    "Dactylagnus peratikos",
    "Dactyloscopus amnis",
    "Dactyloscopus boehlkei",
    "Dactyloscopus byersi",
    "Dactyloscopus comptus",
    "Dactyloscopus crossotus",
    "Dactyloscopus elongatus",
    "Dactyloscopus fallax",
    "Dactyloscopus fimbriatus",
    "Dactyloscopus foraminosus",
    "Dactyloscopus heraldi",
    "Dactyloscopus insulatus",
    "Dactyloscopus lunaticus",
    "Dactyloscopus metoecus",
    "Dactyloscopus minutus",
    "Dactyloscopus moorei",
    "Dactyloscopus poeyi",
    "Dactyloscopus tridigitatus",
    "Dactyloscopus zelotes",
    "Gillellus arenicola",
    "Gillellus chathamensis",
    "Gillellus greyae",
    "Gillellus healae",
    "Gillellus inescatus",
    "Gillellus jacksoni",
    "Gillellus ornatus",
    "Gillellus searcheri",
    "Heteristius cinctus",
    "Leurochilus acon",
    "Myxodagnus belone",
    "Myxodagnus macrognathus",
    "Myxodagnus opercularis",
    "Myxodagnus sagitta",
    "Myxodagnus walkeri",
    "Platygillellus altivelis",
    "Platygillellus brasiliensis",
    "Platygillellus bussingi",
    "Platygillellus rubellulus",
    "Platygillellus smithi",
    "Sindoscopus australis",
    "Storrsia olsoni"
  ],
  "gene_sampling": {
    "12s": [

    ],
    "16s": [
      "Gillellus semicinctus"
    ],
    "4c4": [
      "Dactyloscopus lacteus",
      "Dactyloscopus pectoralis",
      "Gillellus uranidea",
      "Platygillellus rubrocinctus"
    ],
    "coi": [
      "Gillellus uranidea",
      "Platygillellus rubrocinctus"
    ],
    "cytb": [

    ],
    "enc1": [

    ],
    "ficd": [

    ],
    "glyt": [

    ],
    "hoxc6a": [
      "Platygillellus rubrocinctus"
    ],
    "kiaa1239": [
      "Platygillellus rubrocinctus"
    ],
    "myh6": [
      "Gillellus semicinctus",
      "Platygillellus rubrocinctus"
    ],
    "nd2": [

    ],
    "nd4": [

    ],
    "panx2": [
      "Platygillellus rubrocinctus"
    ],
    "plagl2": [
      "Gillellus semicinctus"
    ],
    "ptr": [
      "Gillellus semicinctus"
    ],
    "rag1": [
      "Dactyloscopus lacteus",
      "Gillellus semicinctus",
      "Gillellus uranidea",
      "Platygillellus rubrocinctus"
    ],
    "rag2": [

    ],
    "rhodopsin": [
      "Dactyloscopus lacteus",
      "Gillellus uranidea",
      "Platygillellus rubrocinctus"
    ],
    "ripk4": [

    ],
    "sh3px3": [
      "Gillellus semicinctus",
      "Platygillellus rubrocinctus"
    ],
    "sidkey": [

    ],
    "sreb2": [

    ],
    "svep1": [

    ],
    "tbr1": [
      "Gillellus semicinctus"
    ],
    "vcpip": [

    ],
    "zic1": [
      "Gillellus semicinctus",
      "Platygillellus rubrocinctus"
    ]
  },
  "taxonomy": {
    "class": [
      "Actinopteri"
    ],
    "cohort": [
      "Euteleosteomorpha"
    ],
    "division": [
      "Euacanthomorphacea"
    ],
    "family": [
      "Dactyloscopidae"
    ],
    "infraclass": [
      "Teleostei"
    ],
    "infracohort": [
      "Eurypterygia"
    ],
    "infraorder": [

    ],
    "megacohort": [
      "Osteoglossocephalai"
    ],
    "order": [
      "Blenniiformes"
    ],
    "section": [
      "Ctenosquamata"
    ],
    "series": [
      "Ovalentaria"
    ],
    "subclass": [
      "Neopterygii"
    ],
    "subcohort": [
      "Neoteleostei"
    ],
    "subdivision": [
      "Percomorphaceae"
    ],
    "suborder": [
      "Blennioidei"
    ],
    "subsection": [
      "Acanthomorphata"
    ],
    "supercohort": [
      "Clupeocephala"
    ],
    "superorder": [
      "Blenniimorphae"
    ]
  },
  "tiprates_dr": {
    "Dactyloscopus lacteus": 0.1394,
    "Dactyloscopus pectoralis": 0.1273,
    "Gillellus semicinctus": 0.1812,
    "Gillellus uranidea": 0.1732,
    "Platygillellus rubrocinctus": 0.0969
  },
  "tiprates_bamm_lambda": {
    "Dactyloscopus lacteus": 0.0935,
    "Dactyloscopus pectoralis": 0.0935,
    "Gillellus semicinctus": 0.0935,
    "Gillellus uranidea": 0.0935,
    "Platygillellus rubrocinctus": 0.0935
  },
  "tiprates_bamm_mu": {
    "Dactyloscopus lacteus": 0.0032,
    "Dactyloscopus pectoralis": 0.0032,
    "Gillellus semicinctus": 0.0032,
    "Gillellus uranidea": 0.0032,
    "Platygillellus rubrocinctus": 0.0032
  },
  "mean_dr": 0.1436,
  "mean_bamm_lambda": 0.0935,
  "mean_bamm_mu": 0.0032,
  "matrix_phylip": "downloads/taxonomy/family/Dactyloscopidae.phylip.xz",
  "matrix_nexus": "downloads/taxonomy/family/Dactyloscopidae.nex.xz",
  "chronogram": "downloads/taxonomy/family/Dactyloscopidae.tre",
  "phylogram": "downloads/taxonomy/family/Dactyloscopidae_phylogram.tre",
  "rogues": [

  ]
}